traffic_light_controller.v
module traffic_controller(clk, reset, req, ss, ml, sl, wl);

	
	input clk, reset, req, ss;
	output wl;
    output[1:0] ml, sl; // 00 = Green, 01 = Yellow, 10 = Red
	
    reg [2:0] state;
    reg sensorState;
	reg wlReg;
	reg [1:0] mlReg, slReg;
    integer secs; // passed seconds
    parameter [2:0] mlGreen = 3'b000;   // Main light is green & Side light is red
    parameter [2:0] mlYellow = 3'b001;  // Main light is yellow & Side light is red 
    parameter [2:0] slGreen = 3'b010;   // Side light is green & Main light is red
    parameter [2:0] slYellow = 3'b011;  // Side light is Yellow & Main light is red
    parameter [2:0] wlOn = 3'b100;  // Walk light is green
    
    always @(posedge reset) begin
        state = mlGreen;
        sensorState = 0;
        secs = 0;
    end

    always @(posedge clk) begin
        
        case (state)
            mlGreen: begin
                if (secs != 0 && secs % 3 == 0) begin
                    
                    if ((secs == 9 && sensorState == 1) || (secs == 12 && sensorState == 0)) begin
                        state = mlYellow;
                        sensorState = 0;
                        secs = 0;
                    end
                    if (secs == 6 && ss == 1)
                        sensorState = 1'b1;
                        //secs = secs + 3;
                end
            end
            mlYellow: begin
                if (secs == 2) begin
                    secs = 0;
                    state = req == 1'b1 ? wlOn : slGreen;
                end
            end
            slGreen: begin
                //secs = secs + 1;
                if (secs == 6 && ss == 1)
                    sensorState = 1;
                else if (secs == 6 && ss == 0) begin
                    secs = 0;
                    state = slYellow;
                end
                else if (secs == 9 && sensorState == 1) begin
                    secs = 0;
                    sensorState = 0;
                    state = slYellow;
                end
            end
            slYellow: begin
                //secs = secs + 1;
                if (secs == 2) begin
                    secs = 0;
                    state = mlGreen;
                end
            end
            wlOn: begin
                //secs = secs + 1;
                if (secs == 3) begin
                    secs = 0;
                    state = slGreen;
                end
            end
			endcase
        secs = secs + 1;

    end
	 
	 always @(state) begin
		case (state)
			mlGreen: begin 
				mlReg = 2'b00;
				slReg = 2'b10;
				wlReg = 1'b0;
			end
			mlYellow: begin
				mlReg = 2'b01;
				slReg = 2'b10;
				wlReg = 1'b0;
			end
			slGreen: begin
				mlReg = 2'b10;
				slReg = 2'b00;
				wlReg = 1'b0;
			end
			slYellow: begin
				mlReg = 2'b10;
				slReg = 2'b01;
				wlReg = 1'b0;
			end
			wlOn: begin
				mlReg = 2'b10;
				slReg = 2'b10;
				wlReg = 1'b1;
			end
		endcase
	 end
	 
	 assign ml = mlReg;
	 assign sl = slReg;
	 assign wl = wlReg;

endmodule

traffic_light_controller_tb.v
`timescale 1ms / 1ms
`include "traffic_light_controller.v"

module traffic_light_controller_tb;

    reg clk, reset, req, ss; // input
    wire wl; // output
    wire[1:0] ml, sl;

traffic_controller uut(clk, reset, req, ss, ml, sl, wl);

initial begin
    
    $dumpfile("test_tb.vcd");
    $dumpvars(0, traffic_light_controller_tb);

    // reset
    reset = 1; 
    ss = 0; 
    req = 0;
    clk = 0;
    #200

    // start clock
    // 1 s
    clk = 1; 
    #50

    clk = 0; 
    #50

    // 2 s
    clk = 1; 
    #50

    clk = 0; 
    #50

    // 3 s
    clk = 1; 
    #50

    clk = 0; 
    #50

    // 4 s
    clk = 1; 
    #50

    clk = 0; 
    #50

    // 5 s
    clk = 1; 
    #50

    clk = 0; 
    #50

    // 6 s
    clk = 1; 
    #50

    clk = 0; 
    #50

    // 7 s
    clk = 1; 
    #50

    clk = 0; 
    #50

    // 8 s
    clk = 1; 
    #50

    clk = 0; 
    #50

    // 9 s
    clk = 1; 
    #50

    clk = 0; 
    #50

    // 10 s
    clk = 1; 
    #50

    clk = 0; 
    #50

    // 11 s
    clk = 1; 
    #50

    clk = 0; 
    #50

    // 12 s
    clk = 1; 
    #50

    clk = 0; 
    #50

    // 13 s
    clk = 1; 
    #50

    clk = 0; 
    #50
    

    $display("test complete");
end

endmodule

test_tb.vcd
$date
	Fri Jan 28 16:00:26 2022
$end
$version
	Icarus Verilog
$end
$timescale
	1ms
$end
$scope module traffic_light_controller_tb $end
$var wire 1 ! wl $end
$var wire 2 " sl [1:0] $end
$var wire 2 # ml [1:0] $end
$var reg 1 $ clk $end
$var reg 1 % req $end
$var reg 1 & reset $end
$var reg 1 ' ss $end
$scope module uut $end
$var wire 1 $ clk $end
$var wire 2 ( ml [1:0] $end
$var wire 1 % req $end
$var wire 1 & reset $end
$var wire 2 ) sl [1:0] $end
$var wire 1 ' ss $end
$var wire 1 ! wl $end
$var reg 2 * mlReg [1:0] $end
$var reg 1 + sensorState $end
$var reg 2 , slReg [1:0] $end
$var reg 3 - state [2:0] $end
$var reg 1 . wlReg $end
$var integer 32 / secs [31:0] $end
$upscope $end
$upscope $end
$enddefinitions $end
#0
$dumpvars
b0 /
0.
b0 -
b10 ,
0+
b0 *
b10 )
b0 (
0'
1&
0%
0$
b0 #
b10 "
0!
$end
#200
b1 /
1$
#250
0$
#300
b10 /
1$
#350
0$
#400
b11 /
1$
#450
0$
#500
b100 /
1$
#550
0$
#600
b101 /
1$
#650
0$
#700
b110 /
1$
#750
0$
#800
b111 /
1$
#850
0$
#900
b1000 /
1$
#950
0$
#1000
b1001 /
1$
#1050
0$
#1100
b1010 /
1$
#1150
0$
#1200
b1011 /
1$
#1250
0$
#1300
b1100 /
1$
#1350
0$
#1400
b1 #
b1 (
b1 *
b1 /
b1 -
1$
