traffic_light_controller.v
module traffic_controller(clk, reset, req, ss, ml, sl, wl);

	
	input clk, reset, req, ss;
	output wl;
    output[1:0] ml, sl; // 00 = Green, 01 = Yellow, 10 = Red
	
    reg [2:0] state;
    reg sensorState;
	reg wrReg, wlReg; // walk request register and walk light register
	reg [1:0] mlReg, slReg;
    integer secs; // passed seconds
    parameter [2:0] mlGreen = 3'b000;   // Main light is green & Side light is red
    parameter [2:0] mlYellow = 3'b001;  // Main light is yellow & Side light is red 
    parameter [2:0] slGreen = 3'b010;   // Side light is green & Main light is red
    parameter [2:0] slYellow = 3'b011;  // Side light is Yellow & Main light is red
    parameter [2:0] wlOn = 3'b100;  // Walk light is green
    
    // async reset
    always @(posedge reset) begin
        state = mlGreen;
        sensorState = 0;
        secs = 0;
        wrReg = 0;
    end

    // async button
    always @(posedge req) begin
        wrReg = 1;
    end

    always @(posedge clk) begin
        
        case (state)
            mlGreen: begin
                if (secs != 0 && secs % 3 == 0) begin
                    
                    if ((secs == 9 && sensorState == 1) || (secs == 12 && sensorState == 0)) begin
                        state = mlYellow;
                        sensorState = 0;
                        secs = 0;
                    end
                    if (secs == 6 && ss == 1)
                        sensorState = 1'b1;
                        //secs = secs + 3;
                end
            end
            mlYellow: begin
                if (secs == 2) begin
                    secs = 0;
                    state = wrReg == 1'b1 ? wlOn : slGreen;
                    wrReg = 0;
                end
            end
            slGreen: begin
                //secs = secs + 1;
                if (secs == 6 && ss == 1)
                    sensorState = 1;
                else if (secs == 6 && ss == 0) begin
                    secs = 0;
                    state = slYellow;
                end
                else if (secs == 9 && sensorState == 1) begin
                    secs = 0;
                    sensorState = 0;
                    state = slYellow;
                end
            end
            slYellow: begin
                //secs = secs + 1;
                if (secs == 2) begin
                    secs = 0;
                    state = mlGreen;
                end
            end
            wlOn: begin
                //secs = secs + 1;
                if (secs == 3) begin
                    secs = 0;
                    state = slGreen;
                end
            end
			endcase
        secs = secs + 1;

    end
	 
	 always @(state) begin
		case (state)
			mlGreen: begin 
				mlReg = 2'b00;
				slReg = 2'b10;
				wlReg = 1'b0;
			end
			mlYellow: begin
				mlReg = 2'b01;
				slReg = 2'b10;
				wlReg = 1'b0;
			end
			slGreen: begin
				mlReg = 2'b10;
				slReg = 2'b00;
				wlReg = 1'b0;
			end
			slYellow: begin
				mlReg = 2'b10;
				slReg = 2'b01;
				wlReg = 1'b0;
			end
			wlOn: begin
				mlReg = 2'b10;
				slReg = 2'b10;
				wlReg = 1'b1;
			end
		endcase
	 end
	 
	 assign ml = mlReg;
	 assign sl = slReg;
	 assign wl = wlReg;

endmodule

traffic_light_controller_tb.v
`timescale 1ms / 1ms
`include "traffic_light_controller.v"

module traffic_light_controller_tb;

    reg clk, reset, req, ss; // input
    wire wl; // output
    wire[1:0] ml, sl;

traffic_controller uut(clk, reset, req, ss, ml, sl, wl);

initial begin
    
    $dumpfile("test_tb.vcd");
    $dumpvars(0, traffic_light_controller_tb);

    // reset
    reset = 1; 
    ss = 0; 
    req = 0;
    clk = 0;
    #200

    // start clock
    // 1 s
    clk = 1; 
    #50

    clk = 0; 
    #50

    // 2 s
    clk = 1; 
    #50

    clk = 0; 
    #50

    // 3 s
    clk = 1; 
    #50

    clk = 0; 
    #50

    // 4 s
    clk = 1; 
    #50

    clk = 0; 
    #50

    // 5 s
    clk = 1; 
    #50

    clk = 0; 
    #50

    // 6 s
    clk = 1; 
    #50

    clk = 0; 
    #50

    // 7 s
    clk = 1; 
    #50

    clk = 0; 
    #50

    // 8 s
    clk = 1; 
    #50

    clk = 0; 
    #50

    // 9 s
    clk = 1; 
    #50

    clk = 0; 
    #50

    // 10 s
    clk = 1; 
    #50

    clk = 0; 
    #50

    // 11 s
    clk = 1; 
    #50

    clk = 0; 
    #50

    // 12 s
    clk = 1; 
    #50

    clk = 0; 
    #50

    // 13 s
    clk = 1; 
    #50

    clk = 0; 
    #50

     // 14 s
    clk = 1; 
    #50

    clk = 0; 
    #50

    // 15 s
    clk = 1; 
    #50

    clk = 0; 
    #50

    // 16 s
    clk = 1; 
    #50

    clk = 0; 
    #50

    // 17 s
    clk = 1; 
    #50

    clk = 0; 
    #50

    // 18 s
    clk = 1; 
    #50

    clk = 0; 
    #50

    // 19 s
    clk = 1; 
    #50

    clk = 0; 
    #50

    // 20 s
    clk = 1; 
    #50

    clk = 0; 
    #50

    // 21 s
    clk = 1; 
    #50

    clk = 0; 
    #50

    // 22 s
    clk = 1; 
    #50

    clk = 0; 
    #50

    // 23 s
    ss = 1;
    req = 1;
    clk = 1; 
    #50

    clk = 0; 
    #50

    // 24 s
    clk = 1; 
    req = 0;
    #50

    clk = 0; 
    #50

    // 25 s
    clk = 1; 
    #50

    clk = 0; 
    #50

    // 26 s
    clk = 1; 
    #50

    clk = 0; 
    #50

    // 27 s
    clk = 1; 
    #50

    clk = 0; 
    #50
    
    // 28 s
    clk = 1; 
    #50

    clk = 0; 
    #50
    // 29 s
    clk = 1; 
    #50

    clk = 0; 
    #50

    // 30 s
    clk = 1; 
    #50

    clk = 0; 
    #50
    
    // 31 s
    clk = 1; 
    #50

    clk = 0; 
    #50

    // 32 s
    clk = 1; 
    #50

    clk = 0; 
    #50

    // 33 s
    clk = 1; 
    #50

    clk = 0; 
    #50

    // 34 s
    clk = 1; 
    #50

    clk = 0; 
    #50

    // 35 s
    clk = 1; 
    #50

    clk = 0; 
    #50

    // 36 s
    clk = 1; 
    #50

    clk = 0; 
    #50

    // 37 s
    clk = 1; 
    #50

    clk = 0; 
    #50

    // 38 s
    clk = 1; 
    #50

    clk = 0; 
    #50

    // 39 s
    clk = 1; 
    #50

    clk = 0; 
    #50

    // 40 s
    clk = 1; 
    #50

    clk = 0; 
    #50

    // 41 s
    clk = 1; 
    #50

    clk = 0; 
    #50

    // 42 s
    clk = 1; 
    #50

    clk = 0; 
    #50

    // 43 s
    clk = 1; 
    #50

    clk = 0; 
    #50

    // 44 s
    clk = 1; 
    #50

    clk = 0; 
    #50

    // 45 s
    clk = 1; 
    #50

    clk = 0; 
    #50

    // 46 s
    clk = 1; 
    #50

    clk = 0; 
    #50

    // 47 s
    clk = 1; 
    #50

    clk = 0; 
    #50

    // 48 s
    clk = 1; 
    #50

    clk = 0; 
    #50

    // 49 s
    clk = 1; 
    #50

    clk = 0; 
    #50

    // 50 s
    clk = 1; 
    #50

    clk = 0; 
    #50

    // 51 s
    clk = 1; 
    #50

    clk = 0; 
    #50

    // 52 s
    clk = 1; 
    #50

    clk = 0; 
    #50

    // 53 s
    clk = 1; 
    #50

    clk = 0; 
    #50

    // 54 s
    clk = 1; 
    #50

    clk = 0; 
    #50

    // 55 s
    clk = 1; 
    #50

    clk = 0; 
    #50

    $display("test complete");
end

endmodule

test_tb.vcd
$date
	Mon Jan 31 12:12:00 2022
$end
$version
	Icarus Verilog
$end
$timescale
	1ms
$end
$scope module traffic_light_controller_tb $end
$var wire 1 ! wl $end
$var wire 2 " sl [1:0] $end
$var wire 2 # ml [1:0] $end
$var reg 1 $ clk $end
$var reg 1 % req $end
$var reg 1 & reset $end
$var reg 1 ' ss $end
$scope module uut $end
$var wire 1 $ clk $end
$var wire 2 ( ml [1:0] $end
$var wire 1 % req $end
$var wire 1 & reset $end
$var wire 2 ) sl [1:0] $end
$var wire 1 ' ss $end
$var wire 1 ! wl $end
$var reg 2 * mlReg [1:0] $end
$var reg 1 + sensorState $end
$var reg 2 , slReg [1:0] $end
$var reg 3 - state [2:0] $end
$var reg 1 . wlReg $end
$var reg 1 / wrReg $end
$var integer 32 0 secs [31:0] $end
$upscope $end
$upscope $end
$enddefinitions $end
#0
$dumpvars
b0 0
0/
0.
b0 -
b10 ,
0+
b0 *
b10 )
b0 (
0'
1&
0%
0$
b0 #
b10 "
0!
$end
#200
b1 0
1$
#250
0$
#300
b10 0
1$
#350
0$
#400
b11 0
1$
#450
0$
#500
b100 0
1$
#550
0$
#600
b101 0
1$
#650
0$
#700
b110 0
1$
#750
0$
#800
b111 0
1$
#850
0$
#900
b1000 0
1$
#950
0$
#1000
b1001 0
1$
#1050
0$
#1100
b1010 0
1$
#1150
0$
#1200
b1011 0
1$
#1250
0$
#1300
b1100 0
1$
#1350
0$
#1400
b1 #
b1 (
b1 *
b1 0
b1 -
1$
#1450
0$
#1500
b10 0
1$
#1550
0$
#1600
b0 "
b0 )
b0 ,
b10 #
b10 (
b10 *
b10 -
b1 0
1$
#1650
0$
#1700
b10 0
1$
#1750
0$
#1800
b11 0
1$
#1850
0$
#1900
b100 0
1$
#1950
0$
#2000
b101 0
1$
#2050
0$
#2100
b110 0
1$
#2150
0$
#2200
b1 "
b1 )
b1 ,
b11 -
b1 0
1$
#2250
0$
#2300
b10 0
1$
#2350
0$
#2400
b10 "
b10 )
b10 ,
b0 #
b0 (
b0 *
b0 -
b1 0
1/
1$
1%
1'
#2450
0$
#2500
b10 0
0%
1$
#2550
0$
#2600
b11 0
1$
#2650
0$
#2700
b100 0
1$
#2750
0$
#2800
b101 0
1$
#2850
0$
#2900
b110 0
1$
#2950
0$
#3000
b111 0
1+
1$
#3050
0$
#3100
b1000 0
1$
#3150
0$
#3200
b1001 0
1$
#3250
0$
#3300
b1 #
b1 (
b1 *
b1 0
0+
b1 -
1$
#3350
0$
#3400
b10 0
1$
#3450
0$
#3500
1!
1.
b10 #
b10 (
b10 *
0/
b100 -
b1 0
1$
#3550
0$
#3600
b10 0
1$
#3650
0$
#3700
b11 0
1$
#3750
0$
#3800
0!
0.
b0 "
b0 )
b0 ,
b10 -
b1 0
1$
#3850
0$
#3900
b10 0
1$
#3950
0$
#4000
b11 0
1$
#4050
0$
#4100
b100 0
1$
#4150
0$
#4200
b101 0
1$
#4250
0$
#4300
b110 0
1$
#4350
0$
#4400
b111 0
1+
1$
#4450
0$
#4500
b1000 0
1$
#4550
0$
#4600
b1001 0
1$
#4650
0$
#4700
b1 "
b1 )
b1 ,
b11 -
0+
b1 0
1$
#4750
0$
#4800
b10 0
1$
#4850
0$
#4900
b10 "
b10 )
b10 ,
b0 #
b0 (
b0 *
b0 -
b1 0
1$
#4950
0$
#5000
b10 0
1$
#5050
0$
#5100
b11 0
1$
#5150
0$
#5200
b100 0
1$
#5250
0$
#5300
b101 0
1$
#5350
0$
#5400
b110 0
1$
#5450
0$
#5500
b111 0
1+
1$
#5550
0$
#5600
b1000 0
1$
